LICENSE
MANIFEST.in
README.md
setup.py
aerovane/__init__.py
aerovane/aerovane.py
aerovane/cli.py
aerovane.egg-info/PKG-INFO
aerovane.egg-info/SOURCES.txt
aerovane.egg-info/dependency_links.txt
aerovane.egg-info/entry_points.txt
aerovane.egg-info/requires.txt
aerovane.egg-info/top_level.txt