Metadata-Version: 1.2
Name: aerovane
Version: 0.2.5
Summary: Simple weather report in the terminal
Home-page: https://github.com/dfundingsland/aerovane
Author: David Fundingsland
Author-email: david@fundings.land
License: MIT
Download-URL: https://github.com/dfundingsland/aerovane/master.zip
Platform: UNKNOWN
Classifier: Development Status :: 3 - Alpha
Classifier: Intended Audience :: Developers
Classifier: Natural Language :: English
Classifier: License :: OSI Approved :: MIT License
Classifier: Programming Language :: Python
Classifier: Programming Language :: Python :: 3
Requires-Python: >=3.6
